django_azure_communication_email/__init__.py
django_azure_communication_email/attachment.py
django_azure_communication_email/backend.py
django_azure_communication_email/settings.py
django_azure_communication_email/utils.py
django_azure_communication_email-1.6.0.dist-info/METADATA
django_azure_communication_email-1.6.0.dist-info/WHEEL
django_azure_communication_email-1.6.0.dist-info/licenses/LICENSE
django_azure_communication_email-1.6.0.dist-info/RECORD
