Metadata-Version: 2.4
Name: django-azure-communication-email
Version: 1.6.0
Summary: A Django email backend for Azure Communication Email service.
License: Apache-2.0
License-File: LICENSE
Keywords: django,email,azure
Author: Dmitrii Azarenko
Author-email: dmitrii.azarenko@symphonyai.com
Requires-Python: >=3.10,<3.15
Classifier: Development Status :: 5 - Production/Stable
Classifier: Framework :: Django
Classifier: Framework :: Django :: 3.2
Classifier: Framework :: Django :: 4.0
Classifier: Framework :: Django :: 4.1
Classifier: Framework :: Django :: 4.2
Classifier: Framework :: Django :: 5.0
Classifier: Framework :: Django :: 5.1
Classifier: Framework :: Django :: 5.2
Classifier: Framework :: Django :: 6.0
Classifier: Intended Audience :: Developers
Classifier: License :: OSI Approved :: Apache Software License
Classifier: Operating System :: OS Independent
Classifier: Programming Language :: Python
Classifier: Programming Language :: Python :: 3
Classifier: Programming Language :: Python :: 3.10
Classifier: Programming Language :: Python :: 3.11
Classifier: Programming Language :: Python :: 3.12
Classifier: Programming Language :: Python :: 3.13
Classifier: Programming Language :: Python :: 3.14
Classifier: Topic :: Software Development :: Libraries :: Python Modules
Requires-Dist: Django (>=3.2,<6.1)
Requires-Dist: azure-communication-email (>=1.0,<2.0)
Requires-Dist: azure-identity (>=1.15,<2)
Project-URL: Bug Tracker, https://github.com/retech-us/django-azure-communication-email/issues
Project-URL: Company Website, https://www.symphonyai.com/
Project-URL: Repository, https://github.com/retech-us/django-azure-communication-email
